{
  "__type__": "cc.AnimationClip",
  "_name": "ani_box_out",
  "_objFlags": 0,
  "_rawFiles": null,
  "_duration": 0.3333333333333333,
  "sample": 60,
  "speed": 1,
  "wrapMode": 1,
  "curveData": {
    "paths": {
      "basic_point/num": {
        "props": {
          "position": []
        }
      },
      "basic_point": {
        "props": {
          "position": [
            {
              "frame": 0,
              "value": [
                320,
                932.7501
              ]
            },
            {
              "frame": 0.1,
              "value": [
                319.9921,
                884.6467
              ]
            },
            {
              "frame": 0.21666666666666667,
              "value": [
                319.9841,
                573.1965
              ]
            },
            {
              "frame": 0.3333333333333333,
              "value": [
                319.976,
                225.7455
              ]
            }
          ],
          "opacity": [
            {
              "frame": 0.21666666666666667,
              "value": 255
            },
            {
              "frame": 0.3333333333333333,
              "value": 0
            }
          ]
        }
      },
      "chain_point": {
        "props": {
          "position": [
            {
              "frame": 0,
              "value": [
                320,
                808.4897
              ]
            },
            {
              "frame": 0.1,
              "value": [
                319.9951,
                776.2862
              ]
            },
            {
              "frame": 0.21666666666666667,
              "value": [
                319.9897,
                522.3869
              ]
            },
            {
              "frame": 0.3333333333333333,
              "value": [
                319.9843,
                214.4864
              ]
            }
          ],
          "opacity": [
            {
              "frame": 0.21666666666666667,
              "value": 255
            },
            {
              "frame": 0.3333333333333333,
              "value": 0
            }
          ]
        }
      },
      "win_point/num": {
        "props": {
          "position": []
        }
      },
      "win_point": {
        "props": {
          "position": [
            {
              "frame": 0,
              "value": [
                320,
                684.2296
              ]
            },
            {
              "frame": 0.1,
              "value": [
                319.9951,
                668.9255
              ]
            },
            {
              "frame": 0.21666666666666667,
              "value": [
                319.9897,
                478.0772
              ]
            },
            {
              "frame": 0.3333333333333333,
              "value": [
                319.9843,
                213.2268
              ]
            }
          ],
          "opacity": [
            {
              "frame": 0.21666666666666667,
              "value": 255
            },
            {
              "frame": 0.3333333333333333,
              "value": 0
            }
          ]
        }
      },
      "Text_18": {
        "props": {
          "opacity": [
            {
              "frame": 0,
              "value": 255
            },
            {
              "frame": 0.11666666666666667,
              "value": 0
            }
          ]
        }
      }
    }
  },
  "events": []
}